Metadata-Version: 2.4
Name: llama-index-embeddings-alephalpha
Version: 0.4.1
Summary: llama-index embeddings alephalpha integration
Author-email: Your Name <you@example.com>
License-Expression: MIT
License-File: LICENSE
Requires-Python: <4.0,>=3.9
Requires-Dist: aleph-alpha-client<8,>=7.0.1
Requires-Dist: llama-index-core<0.15,>=0.13.0
